<?xml version="1.0" encoding="UTF-8"?>
<?xml-model href="http://dplava.lib.virginia.edu/dplava.xsd"
    type="application/xml" schematypens="http://purl.oclc.org/dsdl/schematron"?>
<mdRecord xmlns="http://dplava.lib.virginia.edu"
    xmlns:xsi="http://www.w3.org/2001/XMLSchema-instance"
    xmlns:dc="http://purl.org/dc/elements/1.1/"
    xmlns:dcterms="http://purl.org/dc/terms/"
    xmlns:rdf="http://www.w3.org/1999/02/22-rdf-syntax-ns#"
    xmlns:edm="http://www.europeana.eu/schemas/edm/"
    xsi:schemaLocation="http://dplava.lib.virginia.edu dplava.xsd">
    <dcterms:identifier>uva-lib:1219597</dcterms:identifier>
    <dcterms:title>Our battle-flag</dcterms:title>
    <dcterms:provenance>University of Virginia Library</dcterms:provenance>
    <dcterms:creator>Willett, Edward, 1830-1889</dcterms:creator>
    <dcterms:created>1863/1864</dcterms:created>
    <dcterms:medium>print</dcterms:medium>
    <dcterms:extent>1 sheet ([1] p.) : ill. ; 21 x 13 cm.</dcterms:extent>
    <dcterms:publisher>Published by Chas. Magnus, 12 Frankfort St N.Y.</dcterms:publisher>
    <dcterms:subject>Flags</dcterms:subject>
    <dcterms:subject>War songs</dcterms:subject>
    <dcterms:subject>Soldiers</dcterms:subject>
    <dcterms:subject>Death songs</dcterms:subject>
    <dcterms:subject>Patriotic music</dcterms:subject>
    <dcterms:subject>History</dcterms:subject>
    <dcterms:type>Text</dcterms:type>
    <dcterms:spatial>United States</dcterms:spatial>
    <dcterms:spatial>New York (State)</dcterms:spatial>
    <dcterms:spatial>New York (City)</dcterms:spatial>
    <dcterms:language>eng</dcterms:language>
    <edm:hasType>Broadsides-New York (State)-New York-1860-1870.</edm:hasType>
    <edm:hasType>Song sheets-New York (State)-New York-1860-1870.</edm:hasType>
    <dcterms:temporal>Civil War, 1861-1865</dcterms:temporal>
    <dcterms:isReferencedBy>http://search.lib.virginia.edu/catalog/uva-lib:1219597/iiif/manifest.json</dcterms:isReferencedBy>
    <dcterms:rights>http://rightsstatements.org/vocab/NKC/1.0/</dcterms:rights>
    <edm:isShownAt>http://search.lib.virginia.edu/catalog/uva-lib:1219597</edm:isShownAt>
    <edm:preview>https://iiif.lib.virginia.edu/iiif/uva-lib:1219731/full/!300,300/0/default.jpg</edm:preview>
</mdRecord>
