<?xml version="1.0" encoding="UTF-8"?>
<?xml-model href="http://dplava.lib.virginia.edu/dplava.xsd"
    type="application/xml" schematypens="http://purl.oclc.org/dsdl/schematron"?>
<mdRecord xmlns="http://dplava.lib.virginia.edu"
    xmlns:xsi="http://www.w3.org/2001/XMLSchema-instance"
    xmlns:dc="http://purl.org/dc/elements/1.1/"
    xmlns:dcterms="http://purl.org/dc/terms/"
    xmlns:rdf="http://www.w3.org/1999/02/22-rdf-syntax-ns#"
    xmlns:edm="http://www.europeana.eu/schemas/edm/"
    xsi:schemaLocation="http://dplava.lib.virginia.edu dplava.xsd">
    <dcterms:identifier>uva-lib:1126139</dcterms:identifier>
    <dcterms:title>Twilight ramble : variations for the piano</dcterms:title>
    <dcterms:provenance>University of Virginia Library</dcterms:provenance>
    <dcterms:creator>Thilow, C. W.</dcterms:creator>
    <dcterms:created>1857</dcterms:created>
    <dcterms:medium>print</dcterms:medium>
    <dcterms:extent>7 p. of music ; 34 cm.</dcterms:extent>
    <dcterms:publisher>Miller &amp; Beacham</dcterms:publisher>
    <dcterms:subject>Variations (Piano)</dcterms:subject>
    <dcterms:subject>Piano music</dcterms:subject>
    <dcterms:type>notated music</dcterms:type>
    <dcterms:language>zxx</dcterms:language>
    <dcterms:isReferencedBy>http://search.lib.virginia.edu/catalog/uva-lib:1126139/iiif/manifest.json</dcterms:isReferencedBy>
    <dcterms:rights>http://rightsstatements.org/vocab/NoC-US/1.0/</dcterms:rights>
    <edm:isShownAt>http://search.lib.virginia.edu/catalog/uva-lib:1126139</edm:isShownAt>
    <edm:preview>https://iiif.lib.virginia.edu/iiif/uva-lib:1126140/full/!300,300/0/default.jpg</edm:preview>
</mdRecord>
