<?xml version="1.0" encoding="UTF-8"?>
<?xml-model href="http://dplava.lib.virginia.edu/dplava.xsd"
    type="application/xml" schematypens="http://purl.oclc.org/dsdl/schematron"?>
<mdRecord xmlns="http://dplava.lib.virginia.edu"
    xmlns:xsi="http://www.w3.org/2001/XMLSchema-instance"
    xmlns:dc="http://purl.org/dc/elements/1.1/"
    xmlns:dcterms="http://purl.org/dc/terms/"
    xmlns:rdf="http://www.w3.org/1999/02/22-rdf-syntax-ns#"
    xmlns:edm="http://www.europeana.eu/schemas/edm/"
    xsi:schemaLocation="http://dplava.lib.virginia.edu dplava.xsd">
    <dcterms:identifier>uva-lib:730700</dcterms:identifier>
    <dcterms:title>Les sept Pseaulmes de la penitence de David</dcterms:title>
    <dcterms:provenance>University of Virginia Library</dcterms:provenance>
    <dcterms:creator>Aretino, Pietro, 1492-1556</dcterms:creator>
    <dcterms:created>1540</dcterms:created>
    <dcterms:medium>print</dcterms:medium>
    <dcterms:extent>109, [3] p. ; 17 cm. (8vo)</dcterms:extent>
    <dcterms:publisher>chez Seb. Gryphius</dcterms:publisher>
    <dcterms:type>Text</dcterms:type>
    <dcterms:spatial>France</dcterms:spatial>
    <dcterms:spatial>Lyon</dcterms:spatial>
    <dcterms:language>fre</dcterms:language>
    <dcterms:language>ita</dcterms:language>
    <dcterms:isReferencedBy>http://search.lib.virginia.edu/catalog/uva-lib:730700/iiif/manifest.json</dcterms:isReferencedBy>
    <dcterms:rights>http://rightsstatements.org/vocab/NoC-US/1.0/</dcterms:rights>
    <edm:isShownAt>http://search.lib.virginia.edu/catalog/uva-lib:730700</edm:isShownAt>
    <edm:preview>https://iiif.lib.virginia.edu/iiif/uva-lib:730887/full/!300,300/0/default.jpg</edm:preview>
</mdRecord>
